PartSegCore_compiled_backend/__init__.py
PartSegCore_compiled_backend/_fast_unique.cp310-win_amd64.pyd
PartSegCore_compiled_backend/_fast_unique.pyi
PartSegCore_compiled_backend/_napari_mapping.cp310-win_amd64.pyd
PartSegCore_compiled_backend/calc_bounds.cp310-win_amd64.pyd
PartSegCore_compiled_backend/calc_bounds.pyi
PartSegCore_compiled_backend/color_image_cython.cp310-win_amd64.pyd
PartSegCore_compiled_backend/color_image_cython.pyi
PartSegCore_compiled_backend/fast_unique.py
PartSegCore_compiled_backend/multiscale_opening/__init__.py
PartSegCore_compiled_backend/multiscale_opening/mso.h
PartSegCore_compiled_backend/multiscale_opening/mso_bind.cp310-win_amd64.pyd
PartSegCore_compiled_backend/multiscale_opening/mso_bind.pyi
PartSegCore_compiled_backend/multiscale_opening/my_queue.h
PartSegCore_compiled_backend/napari_mapping.py
PartSegCore_compiled_backend/sprawl_utils/__init__.py
PartSegCore_compiled_backend/sprawl_utils/distance_utils.pxd
PartSegCore_compiled_backend/sprawl_utils/euclidean_cython.cp310-win_amd64.pyd
PartSegCore_compiled_backend/sprawl_utils/euclidean_cython.pyi
PartSegCore_compiled_backend/sprawl_utils/find_split.py
PartSegCore_compiled_backend/sprawl_utils/find_split.pyi
PartSegCore_compiled_backend/sprawl_utils/fuzzy_distance.cp310-win_amd64.pyd
PartSegCore_compiled_backend/sprawl_utils/global_consts.h
PartSegCore_compiled_backend/sprawl_utils/my_queue.h
PartSegCore_compiled_backend/sprawl_utils/path_sprawl_cython.cp310-win_amd64.pyd
PartSegCore_compiled_backend/sprawl_utils/path_sprawl_cython.pyi
PartSegCore_compiled_backend/sprawl_utils/sprawl_utils.cp310-win_amd64.pyd
PartSegCore_compiled_backend/sprawl_utils/sprawl_utils.pyi
PartSegCore_compiled_backend/triangulate.cp310-win_amd64.pyd
PartSegCore_compiled_backend/triangulation/debug_util.hpp
PartSegCore_compiled_backend/triangulation/intersection.hpp
PartSegCore_compiled_backend/triangulation/point.hpp
PartSegCore_compiled_backend/triangulation/triangulate.hpp
partsegcore_compiled_backend-0.15.13.dist-info/METADATA
partsegcore_compiled_backend-0.15.13.dist-info/WHEEL
partsegcore_compiled_backend-0.15.13.dist-info/licenses/LICENSE.txt
partsegcore_compiled_backend-0.15.13.dist-info/RECORD
