Metadata-Version: 2.2
Name: PartSegCore_compiled_backend
Version: 0.15.13
Summary: PartSegCore compiled backend,
Keywords: bioimaging
Author-Email: Grzegorz Bokota <g.bokota@cent.uw.edu.pl>
License: BSD-3-Clause
Classifier: Development Status :: 3 - Alpha
Classifier: License :: OSI Approved :: BSD License
Classifier: Operating System :: OS Independent
Classifier: Programming Language :: Python :: 3
Classifier: Programming Language :: Python :: 3 :: Only
Classifier: Programming Language :: Python :: 3.9
Classifier: Programming Language :: Python :: 3.10
Classifier: Programming Language :: Python :: 3.11
Classifier: Programming Language :: Python :: 3.12
Classifier: Programming Language :: Python :: Implementation :: CPython
Classifier: Topic :: Scientific/Engineering :: Bio-Informatics
Project-URL: Homepage, https://4dnucleome.cent.uw.edu.pl/PartSeg/
Project-URL: Documentation, https://partsegcore-compiled-backend.readthedocs.io/en/stable/
Project-URL: Source Code, https://github.com/4DNucleome/PartSegCore-compiled-backend
Requires-Python: >=3.9
Requires-Dist: numpy>=1.23.5
Provides-Extra: test
Requires-Dist: pytest>=7.0.0; extra == "test"
Provides-Extra: docs
Requires-Dist: sphinx>=5.0.0; extra == "docs"
